pyRestTable/LICENSE.txt
pyRestTable/__init__.py
pyRestTable/_version.py
pyRestTable/rest_table.py
pyRestTable/simple.py
pyRestTable/tests/__init__.py
pyRestTable/tests/test_dict_table.py
pyRestTable/tests/test_results.py
pyRestTable-2020.0.10.dist-info/METADATA
pyRestTable-2020.0.10.dist-info/WHEEL
pyRestTable-2020.0.10.dist-info/top_level.txt
pyRestTable-2020.0.10.dist-info/RECORD
