Metadata-Version: 2.1
Name: pyRestTable
Version: 2020.0.10
Summary: Format a nice table in reST (reStructuredText) from Python.
Author-email: Pete Jemian <prjemian+pyRestTable@gmail.com>
Maintainer-email: Pete Jemian <prjemian+pyRestTable@gmail.com>
License: Creative Commons Attribution 4.0 International Public License
Project-URL: Homepage, https://prjemian.github.io/pyRestTable/
Project-URL: Bug Tracker, https://github.com/prjemian/pyRestTable/issues
Keywords: reST,table,documentation
Classifier: Development Status :: 6 - Mature
Classifier: Environment :: Console
Classifier: Intended Audience :: Developers
Classifier: License :: CC0 1.0 Universal (CC0 1.0) Public Domain Dedication
Classifier: License :: Freely Distributable
Classifier: License :: Public Domain
Classifier: Programming Language :: Python
Classifier: Programming Language :: Python :: 3
Classifier: Programming Language :: Python :: 3.9
Classifier: Programming Language :: Python :: 3.10
Classifier: Programming Language :: Python :: 3.11
Classifier: Programming Language :: Python :: 3.12
Classifier: Programming Language :: Python :: 3.13
Classifier: Topic :: Documentation
Classifier: Topic :: Documentation :: Sphinx
Classifier: Topic :: Software Development
Classifier: Topic :: Software Development :: Documentation
Classifier: Topic :: Text Processing :: Markup
Classifier: Topic :: Utilities
Requires-Python: >=3.9
Requires-Dist: lxml
